{
    "songs": [
        {
            "type": "spotify",
            "id": "3Vv87GEXScl3IOGEhZ1uNa",
            "day_of_year": "06/25",
            "song": "Stars Fell on Alabama",
            "artist": "She & Him",
            "note": ""
        },
        {
            "type": "spotify",
            "id": "4VywXu6umkIQ2OS0m1I79y",
            "day_of_year": "06/26",
            "song": "Better Together",
            "artist": "Jack Johnson",
            "note": ""
        },
        {
            "type": "spotify",
            "id": "1NrbnHlR2BFREcyWXHIHip",
            "day_of_year": "06/27",
            "song": "When I'm Sixty Four",
            "artist": "The Beatles",
            "note": ""
        },
        {
            "type": "spotify",
            "id": "3L8KZiaX41m3hbxavdBcpx",
            "day_of_year": "06/28",
            "song": "Mario Kart Love Song",
            "artist": "Sam Hart",
            "note": ""
        },
        {
            "type": "spotify",
            "id": "0TJiGLT3w6HRsd5SSdEUWZ",
            "day_of_year": "06/29",
            "song": "Angel in the Snow",
            "artist": "Elliott Smith",
            "note": ""
        },
        {
            "type": "spotify",
            "id": "2GBPG1wjcFMaIyHpkL28Zt",
            "day_of_year": "06/30",
            "song": "Happiness Loves Company",
            "artist": "Red Hot Chili Peppers",
            "note": ""
        },
        {
            "type": "spotify",
            "id": "1WkMMavIMc4JZ8cfMmxHkI",
            "day_of_year": "07/01",
            "song": "Can't Stop the Feeling",
            "artist": "Justin Timberlake",
            "note": ""
        },
        {
            "type": "spotify",
            "id": "6AeQlMyRzvSl1nkFztZyKl",
            "day_of_year": "07/02",
            "song": "Issues",
            "artist": "Julia Michaels",
            "note": ""
        },
        {
            "type": "spotify",
            "id": "19XbNdlmKfqUZdhpLJuxVC",
            "day_of_year": "07/03",
            "song": "Thirteen",
            "artist": "Elliott Smith",
            "note": ""
        },
        {
            "type": "spotify",
            "id": "3ypXaNibspfxvUIKpzUkfz",
            "day_of_year": "07/04",
            "song": "Echo",
            "artist": "Incubus",
            "note": ""
        },
        {
            "type": "spotify",
            "id": "2vyWFovtrd43gdcirx4anV",
            "day_of_year": "07/05",
            "song": "Bubble Toes",
            "artist": "Jack Johnson",
            "note": ""
        },
        {
            "type": "spotify",
            "id": "1aMiDQtbZlTAq93SsbG1wN",
            "day_of_year": "07/06",
            "song": "Leaves in the River",
            "artist": "Sea Wolf",
            "note": ""
        },
        {
            "type": "spotify",
            "id": "1ewyFsfVbuN5lqx7neaYIv",
            "day_of_year": "07/07",
            "song": "Yankee Bayonet",
            "artist": "The Decemberists",
            "note": ""
        },
        {
            "type": "spotify",
            "id": "3kZC0ZmFWrEHdUCmUqlvgZ",
            "day_of_year": "07/08",
            "song": "I Will Follow You into the Dark",
            "artist": "Death Cab for Cutie",
            "note": ""
        },
        {
            "type": "spotify",
            "id": "7w5cxTEzp1rfV3KCy0Bd5N",
            "day_of_year": "07/09",
            "song": "Home",
            "artist": "Edward Sharpe & The Magnetic Zeros",
            "note": ""
        },
        {
            "type": "spotify",
            "id": "4pbG9SUmWIvsROVLF0zF9s",
            "day_of_year": "07/10",
            "song": "I Want to Hold Your Hand",
            "artist": "The Beatles",
            "note": ""
        },
        {
            "type": "spotify",
            "id": "0q6LuUqGLUiCPP1cbdwFs3",
            "day_of_year": "07/11",
            "song": "On Melancholy Hill",
            "artist": "Gorillaz",
            "note": ""
        },
        {
            "type": "youtube",
            "id": "umJl8t7G0q8",
            "day_of_year": "07/12",
            "song": "Secret Tunnel",
            "artist": "Avatar The Last Airbender",
            "note": ""
        },
        {
            "type": "spotify",
            "id": "2pFPmAzFFPxWPHGM64wtRQ",
            "day_of_year": "07/13",
            "song": "Alive with the Glory of Love",
            "artist": "Say Anything",
            "note": ""
        },
        {
            "type": "spotify",
            "id": "6YB4zqzheD7QbJJBQ1pA08",
            "day_of_year": "07/14",
            "song": "When We First Met",
            "artist": "Hellogoodbye",
            "note": "\"All I see is where our days repeat, And our love goes on, As our hair grows long\""
        },
        {
            "type": "spotify",
            "id": "2MVwrvjmcdt4MsYYLCYMt8",
            "day_of_year": "07/15",
            "song": "Tighten Up",
            "artist": "The Black Keys",
            "note": "\"I'm bound to fall, bound to fall for you\""
        },
        {
            "type": "spotify",
            "id": "0o9Vr0BGIQPh32staLHcuU",
            "day_of_year": "07/16",
            "song": "Bidi Bidi Bom Bom",
            "artist": "Selena",
            "note": ""
        },
        {
            "type": "spotify",
            "id": "3tPz0YQNXXfzXbQtLJOj0H",
            "day_of_year": "07/17",
            "song": "Happy Song",
            "artist": "Kate Micucci",
            "note": ""
        },
        {
            "type": "spotify",
            "id": "754kgU5rWscRTfvlsuEwFp",
            "day_of_year": "07/18",
            "song": "Kiss Me",
            "artist": "Sixpence None The Richer",
            "note": ""
        },
        {
            "type": "spotify",
            "id": "2Pr1nZpt8A8WP7QYpyq6L3",
            "day_of_year": "07/19",
            "song": "Wildflowers",
            "artist": "Tom Petty",
            "note": ""
        },
        {
            "type": "spotify",
            "id": "7iDa6hUg2VgEL1o1HjmfBn",
            "day_of_year": "07/20",
            "song": "Meant to Be (feat. Florida Georgia Line)",
            "artist": "Bebe Rexha",
            "note": "Little Bee"
        },
        {
            "type": "spotify",
            "id": "5VIfacsWytkcgr7aTt8Tql",
            "day_of_year": "07/21",
            "song": "A Whole New World",
            "artist": "Lea Salonga, Brad Kane",
            "note": ""
        },
        {
            "type": "spotify",
            "id": "4JafeLQF3W7nTpaqfDDyLv",
            "day_of_year": "07/22",
            "song": "Compliment Each Other Like Colors",
            "artist": "PlayRadioPlay!",
            "note": ""
        },
        {
            "type": "spotify",
            "id": "00WvmRXTkPBZNhhRK3xfdy",
            "day_of_year": "07/23",
            "song": "As Long As You Love Me",
            "artist": "Backstreet Boys",
            "note": ""
        },
        {
            "type": "spotify",
            "id": "0hDQV9X1Da5JrwhK8gu86p",
            "day_of_year": "07/24",
            "song": "Maps",
            "artist": "Yeah Yeah Yeahs",
            "note": ""
        },
        {
            "type": "spotify",
            "id": "1uGPqR2OCNimv0kPiLmA35",
            "day_of_year": "07/25",
            "song": "Honey Come Home",
            "artist": "The Head and the Heart",
            "note": "Sometimes we get in arguments, but I always want to figure it out with you."
        },
        {
            "type": "spotify",
            "id": "5YqpHuXpFjDVZ7tY1ClFll",
            "day_of_year": "07/26",
            "song": "Heartbeats",
            "artist": "José González",
            "note": ""
        },
        {
            "type": "spotify",
            "id": "3AJwUDP919kvQ9QcozQPxg",
            "day_of_year": "07/27",
            "song": "Yellow",
            "artist": "Coldplay",
            "note": ""
        },
        {
            "type": "spotify",
            "id": "6jX5mso4x00c1EiNMrTU9U",
            "day_of_year": "07/28",
            "song": "Please Mr. Postman",
            "artist": "The Marvelettes",
            "note": "I'll always send you a letter"
        },
        {
            "type": "spotify",
            "id": "1PyPK82Vd79mBJcuqA4Dv1",
            "day_of_year": "07/29",
            "song": "Say Yes",
            "artist": "Elliott Smith",
            "note": ""
        },
        {
            "type": "spotify",
            "id": "7MXK7DwU1DpGFTA31AZW6S",
            "day_of_year": "07/30",
            "song": "Baby's Got Sauce",
            "artist": "G. Love & Special Sauce",
            "note": ""
        },
        {
            "type": "spotify",
            "id": "5CRIDz2sf4C7UCCDPALtyn",
            "day_of_year": "07/31",
            "song": "Christmas Island",
            "artist": "LAKE",
            "note": ""
        },
        {
            "type": "spotify",
            "id": "3LStjSO0xG0FkvUmH0MNKX",
            "day_of_year": "08/01",
            "song": "He Gives His Love To Me",
            "artist": "She & Him",
            "note": ""
        },
        {
            "type": "spotify",
            "id": "0rFOs9paloAvEtzwDX1Kmc",
            "day_of_year": "08/02",
            "song": "Bubbly",
            "artist": "Colbie Caillat",
            "note": ""
        },
        {
            "type": "spotify",
            "id": "4TGjfiGfhS8OKXHdghtMh0",
            "day_of_year": "08/03",
            "song": "The Book of Love",
            "artist": "Peter Gabriel",
            "note": "Cheesey!"
        },
        {
            "type": "spotify",
            "id": "2dR5WkrpwylTuT3jRWNufa",
            "day_of_year": "08/04",
            "song": "Fly Me to the Moon",
            "artist": "Frank Sinatra",
            "note": ""
        },
        {
            "type": "spotify",
            "id": "7bqVZBRrNxmrF1iFQLYX2X",
            "day_of_year": "08/05",
            "song": "Such Great Heights",
            "artist": "The Postal Service",
            "note": ""
        },
        {
            "type": "spotify",
            "id": "75Mwp7YsQRk0ZBq1lOdL2T",
            "day_of_year": "08/06",
            "song": "Earth Angel",
            "artist": "The Penguins",
            "note": ""
        },
        {
            "type": "spotify",
            "id": "6kBU9uWqar0Fw2Ws0he11A",
            "day_of_year": "08/07",
            "song": "You Were Meant For Me",
            "artist": "Jewel",
            "note": ""
        },
        {
            "type": "spotify",
            "id": "221bl0jrSfJ1LMgUw36zRJ",
            "day_of_year": "08/08",
            "song": "O Valencia!",
            "artist": "The Decemberists",
            "note": "Like Romeo & Juliet. A little sad, but who doesn't like a dramatic romance?"
        },
        {
            "type": "spotify",
            "id": "3baBQrWBX71zjKXVtVkvN6",
            "day_of_year": "08/09",
            "song": "Grow Old With Me",
            "artist": "John Lennon",
            "note": ""
        },
        {
            "type": "spotify",
            "id": "756CJtQRFSxEx9jV4P9hpA",
            "day_of_year": "08/10",
            "song": "I Believe in a Thing Called Love",
            "artist": "The Darkness",
            "note": ""
        },
        {
            "type": "spotify",
            "id": "60nfOJJ1xFVVAO1qCpngX6",
            "day_of_year": "08/11",
            "song": "Anyone Else But You",
            "artist": "Michael Cera, Ellen Page",
            "note": ""
        },
        {
            "type": "spotify",
            "id": "106R7Z57WYzBAfrXImV30y",
            "day_of_year": "08/12",
            "song": "Wildest Dreams",
            "artist": "Taylor Swift",
            "note": "You are in my dreams"
        },
        {
            "type": "spotify",
            "id": "5kdzVCV0bfSEoy3Ze0PuG5",
            "day_of_year": "08/13",
            "song": "Good Morning",
            "artist": "Gene Kelly, Donald O'Connor, Debbie Reynolds",
            "note": ""
        },
        {
            "type": "spotify",
            "id": "1we6fKUZmxDbVxqs2n2qjw",
            "day_of_year": "08/14",
            "song": "Blue Eyes",
            "artist": "Cary Brothers",
            "note": ""
        },
        {
            "type": "spotify",
            "id": "1ltSMXmvwdwnHcVY6tXKnB",
            "day_of_year": "08/15",
            "song": "Alright For Now",
            "artist": "Tom Petty",
            "note": ""
        },
        {
            "type": "spotify",
            "id": "4aX3n1Pn6jiCbvqBL8eqyP",
            "day_of_year": "08/16",
            "song": "Love Me Do",
            "artist": "The Beatles",
            "note": ""
        },
        {
            "type": "spotify",
            "id": "4RCWB3V8V0dignt99LZ8vH",
            "day_of_year": "08/17",
            "song": "Hey There Delilah",
            "artist": "Plain White T's",
            "note": ""
        },
        {
            "type": "spotify",
            "id": "5uvosCdMlFdTXhoazkTI5R",
            "day_of_year": "08/18",
            "song": "Light My Fire",
            "artist": "The Doors",
            "note": ""
        },
        {
            "type": "spotify",
            "id": "5yc59J3MR3tVDPTOgwgRI5",
            "day_of_year": "08/19",
            "song": "Soul Meets Body",
            "artist": "Death Cab for Cutie",
            "note": ""
        },
        {
            "type": "youtube",
            "id": "WU0uJcLKiqk",
            "day_of_year": "08/20",
            "song": "Oh, Fionna",
            "artist": "Adventure Time",
            "note": ""
        },
        {
            "type": "spotify",
            "id": "7BqBn9nzAq8spo5e7cZ0dJ",
            "day_of_year": "08/21",
            "song": "Just the Way you Are",
            "artist": "Bruno Mars",
            "note": ""
        },
        {
            "type": "spotify",
            "id": "3uPfVXcjnpOjyzI3jb3js4",
            "day_of_year": "08/22",
            "song": "Fly",
            "artist": "Sugar Ray",
            "note": ""
        },
        {
            "type": "spotify",
            "id": "6Fe3Flc9SjE03pqwD6PVQl",
            "day_of_year": "08/23",
            "song": "Amber",
            "artist": "311",
            "note": ""
        },
        {
            "type": "spotify",
            "id": "1fujSajijBpJlr5mRGKHJN",
            "day_of_year": "08/24",
            "song": "The Luckiest",
            "artist": "Ben Folds",
            "note": ""
        },
        {
            "type": "spotify",
            "id": "451GvHwY99NKV4zdKPRWmv",
            "day_of_year": "08/25",
            "song": "Banana Pancakes",
            "artist": "Jack Johnson",
            "note": ""
        },
        {
            "type": "spotify",
            "id": "3B4q6KbHbGV51HO3GznBFF",
            "day_of_year": "08/26",
            "song": "What I Got",
            "artist": "Sublime",
            "note": ""
        },
        {
            "type": "spotify",
            "id": "2rJFFUEl1LURkV0b0OARXx",
            "day_of_year": "08/27",
            "song": "Beauty and the Beast",
            "artist": "Angela Lansbury",
            "note": ""
        },
        {
            "type": "spotify",
            "id": "3U4isOIWM3VvDubwSI3y7a",
            "day_of_year": "08/28",
            "song": "All of Me",
            "artist": "John Legend",
            "note": ""
        },
        {
            "type": "spotify",
            "id": "5l9c6bJmzvftumhz4TMPgk",
            "day_of_year": "08/29",
            "song": "Harvest Moon",
            "artist": "Neil Young",
            "note": "Because I'm still in love with you<br>I want to see you dance again<br>Because I'm still in love with you<br>On this harvest moon."
        },
        {
            "type": "spotify",
            "id": "59aD95hWQCjcStv2UU5Fq6",
            "day_of_year": "08/30",
            "song": "Oh, it is Love",
            "artist": "Hellogoodbye",
            "note": ""
        },
        {
            "type": "spotify",
            "id": "3FK0U3qJYP3E24Vx5QSBWz",
            "day_of_year": "08/31",
            "song": "Belle",
            "artist": "Jack Johnson",
            "note": "Beautiful lady!"
        },
        {
            "type": "spotify",
            "id": "1q6KLpnyB8NMcSBUPVTlwa",
            "day_of_year": "09/01",
            "song": "You and Me",
            "artist": "Tom Petty",
            "note": "\"Wherever that wind might blow, wherever that river rolls, you know I will go with you, just you and me and the road ahead.\""
        },
        {
            "type": "spotify",
            "id": "43z6scIZU2QcEieMQFAJRG",
            "day_of_year": "09/02",
            "song": "There She Goes",
            "artist": "Sixpence None The Richer",
            "note": ""
        },
        {
            "type": "spotify",
            "id": "1rfofaqEpACxVEHIZBJe6W",
            "day_of_year": "09/03",
            "song": "Havana",
            "artist": "Camila Cabello",
            "note": ""
        },
        {
            "type": "spotify",
            "id": "5OiaAaIMYlCZONyDBxqk4G",
            "day_of_year": "09/04",
            "song": "First Day Of My Life",
            "artist": "Bright Eyes ",
            "note": ""
        },
        {
            "type": "spotify",
            "id": "04ZUQ7G8Aa0B7wvg12ypuw",
            "day_of_year": "09/05",
            "song": "Love Of Your Life",
            "artist": "Red Hot Chili Peppers",
            "note": ""
        },
        {
            "type": "spotify",
            "id": "0BFEyqJ9DJXS7gKg0Kj46R",
            "day_of_year": "09/06",
            "song": "You Send Me",
            "artist": "Sam Cooke",
            "note": ""
        },
        {
            "type": "spotify",
            "id": "2Ch7LmS7r2Gy2kc64wv3Bz",
            "day_of_year": "09/07",
            "song": "Die For You",
            "artist": "The Weeknd",
            "note": ""
        },
        {
            "type": "spotify",
            "id": "5bn5FRmh9HbVD2fX7HxcAf",
            "day_of_year": "09/08",
            "song": "This Girl's In Love With You",
            "artist": "She & Him",
            "note": ""
        },
        {
            "type": "spotify",
            "id": "4Dw02sVUfUA67l3fZ9FoKs",
            "day_of_year": "09/09",
            "song": "My Heart Will Go On",
            "artist": "Celine Dion",
            "note": ""
        },
        {
            "type": "spotify",
            "id": "4joiWvli4qJVEW6qZV2i2J",
            "day_of_year": "09/10",
            "song": "All My Loving",
            "artist": "The Beatles",
            "note": ""
        },
        {
            "type": "spotify",
            "id": "0hCB0YR03f6AmQaHbwWDe8",
            "day_of_year": "09/11",
            "song": "Whole Lotta Love",
            "artist": "Led Zeppelin",
            "note": ""
        },
        {
            "type": "spotify",
            "id": "7DEfn4pi2RBnkPcqEO23sy",
            "day_of_year": "09/12",
            "song": "Sweet Darlin'",
            "artist": "She & Him",
            "note": "Sweet darlin', come hold me<br>Just a little bit longer now<br><br>Happy Birthday! Love you!"
        },
        {
            "type": "spotify",
            "id": "0Cvjlph1WGbwZY1PlMEtJY",
            "day_of_year": "09/13",
            "song": "Come Away With Me",
            "artist": "Norah Jones",
            "note": ""
        },
        {
            "type": "spotify",
            "id": "714hERk9U1W8FMYkoC83CO",
            "day_of_year": "09/14",
            "song": "You Sexy Thing",
            "artist": "Hot Chocolate",
            "note": ""
        },
        {
            "type": "spotify",
            "id": "1LeWIs2hP2r5yOQnVuYoI5",
            "day_of_year": "09/15",
            "song": "Ain’t No Mountain High Enough",
            "artist": "Marvin Gaye and Tammi Terrell",
            "note": ""
        },
        {
            "type": "spotify",
            "id": "1G5zh3BaGPh6wi3dwGNxvs",
            "day_of_year": "09/16",
            "song": "I Wanna Hear Your Secrets",
            "artist": "Bob's Burgers",
            "note": ""
        },
        {
            "type": "spotify",
            "id": "5ylLypaOksxWd75YrGtx2N",
            "day_of_year": "09/17",
            "song": "Eight Days a Week",
            "artist": "The Beatles",
            "note": ""
        },
        {
            "type": "spotify",
            "id": "4alHo6RGd0D3OUbTPExTHN",
            "day_of_year": "09/18",
            "song": "Just What I Needed",
            "artist": "The Cars",
            "note": ""
        },
        {
            "type": "spotify",
            "id": "6xEgJMV5NALIfFJkFdvsrN",
            "day_of_year": "09/19",
            "song": "B-A-B-Y",
            "artist": "Carla Thomas",
            "note": "B-A-B-Y Baby"
        },
        {
            "type": "spotify",
            "id": "1EzrEOXmMH3G43AXT1y7pA",
            "day_of_year": "09/20",
            "song": "I'm Yours",
            "artist": "Jason Mraz",
            "note": ""
        },
        {
            "type": "spotify",
            "id": "3ZOEytgrvLwQaqXreDs2Jx",
            "day_of_year": "09/21",
            "song": "Can't Stop",
            "artist": "Red Hot Chili Peppers",
            "note": "The world I love<br>The tears I drop<br>To be part of<br>The wave can't stop<br>Ever wonder if it's all for you"
        },
        {
            "type": "spotify",
            "id": "6jWkZvd1URGktyTTwcpPpB",
            "day_of_year": "09/22",
            "song": "My Girl",
            "artist": "The Temptations",
            "note": ""
        },
        {
            "type": "spotify",
            "id": "3y9ay8ZKpkSAisQVNi5Tau",
            "day_of_year": "09/23",
            "song": "Love Song #16",
            "artist": "Jack Johnson",
            "note": ""
        },
        {
            "type": "spotify",
            "id": "5mdDzJBkQ7Gz7ePDCB397w",
            "day_of_year": "09/24",
            "song": "Little Bird, Little Bird",
            "artist": "Elizabeth Mitchell",
            "note": ""
        },
        {
            "type": "spotify",
            "id": "1fJFuvU2ldmeAm5nFIHcPP",
            "day_of_year": "09/25",
            "song": "First Date",
            "artist": "Blink-182",
            "note": ""
        },
        {
            "type": "spotify",
            "id": "7qiZfU4dY1lWllzX7mPBI3",
            "day_of_year": "09/26",
            "song": "Shape of You",
            "artist": "Ed Sheeran",
            "note": ""
        },
        {
            "type": "spotify",
            "id": "3mNecsYFb6LQg7822DPXCP",
            "day_of_year": "09/27",
            "song": "Absolutely (Story of a Girl)",
            "artist": "Nine Days ",
            "note": ""
        },
        {
            "type": "spotify",
            "id": "3yu55ZR7hjg1jcLwefIrx5",
            "day_of_year": "09/28",
            "song": "Satellite",
            "artist": "Lelia Broussard",
            "note": ""
        },
        {
            "type": "spotify",
            "id": "023OVLNzXhX0j7CxswUt6D",
            "day_of_year": "09/29",
            "song": "Cheerleader",
            "artist": "Omi",
            "note": ""
        },
        {
            "type": "spotify",
            "id": "2yuea8dOVphJMCEZOlnyKf",
            "day_of_year": "09/30",
            "song": "Can't Help Falling In Love",
            "artist": "Ingrid Michaelson",
            "note": ""
        },
        {
            "type": "spotify",
            "id": "6IWzLyhbCsdxl8KwceNuuj",
            "day_of_year": "10/01",
            "song": "Carebear",
            "artist": "MC Chris",
            "note": ""
        },
        {
            "type": "spotify",
            "id": "2MLHyLy5z5l5YRp7momlgw",
            "day_of_year": "10/02",
            "song": "Island in the Sun",
            "artist": "Weezer",
            "note": ""
        },
        {
            "type": "spotify",
            "id": "6ECp64rv50XVz93WvxXMGF",
            "day_of_year": "10/03",
            "song": "This Love",
            "artist": "Maroon 5p",
            "note": ""
        },
        {
            "type": "spotify",
            "id": "5AOhF9yrkU3CG5eMXCrkun",
            "day_of_year": "10/04",
            "song": "I'm a Pirate, You're a Princess",
            "artist": "PlayRadioPlay!",
            "note": ""
        },
        {
            "type": "spotify",
            "id": "2hKdd3qO7cWr2Jo0Bcs0MA",
            "day_of_year": "10/05",
            "song": "Drops of Jupiter",
            "artist": "Train",
            "note": ""
        },
        {
            "type": "spotify",
            "id": "1jnnieDkF1hOlRil2Sgv9i",
            "day_of_year": "10/06",
            "song": "No Other Way",
            "artist": "Jack Johnson",
            "note": ""
        },
        {
            "type": "spotify",
            "id": "7MEDJRQNYJY0nkMpnqrTp7",
            "day_of_year": "10/07",
            "song": "Memories are Made of This",
            "artist": "Johnny Cash",
            "note": ""
        },
        {
            "type": "spotify",
            "id": "05icsRv9AUQHO7GaJszvDx",
            "day_of_year": "10/08",
            "song": "Dance, Dance, Dance",
            "artist": "Red Hot Chili Peppers",
            "note": ""
        },
        {
            "type": "spotify",
            "id": "3s4U7OHV7gnj42VV72eSZ6",
            "day_of_year": "10/09",
            "song": "Rather Be",
            "artist": "Clean Bandit (feat. Jess Glynne)",
            "note": ""
        },
        {
            "type": "spotify",
            "id": "6KqiVlOLfDzJViJVAPym1p",
            "day_of_year": "10/10",
            "song": "All You Need is Love",
            "artist": "The Beatles",
            "note": ""
        },
        {
            "type": "spotify",
            "id": "5lA3pwMkBdd24StM90QrNR",
            "day_of_year": "10/11",
            "song": "P.Y.T. (Pretty Young Thing)",
            "artist": "Michael Jackson",
            "note": ""
        },
        {
            "type": "spotify",
            "id": "7LVHVU3tWfcxj5aiPFEW4Q",
            "day_of_year": "10/12",
            "song": "Fix You",
            "artist": "Coldplay",
            "note": "I will always try to make you feel better"
        },
        {
            "type": "spotify",
            "id": "1R7KbLX0ED0nrqS8iYMaQB",
            "day_of_year": "10/13",
            "song": "Time After Time",
            "artist": "She & Him",
            "note": ""
        },
        {
            "type": "spotify",
            "id": "6StM8f3wq3hWTEeniz382v",
            "day_of_year": "10/14",
            "song": "Date Night",
            "artist": "Bob's Burgers",
            "note": ""
        },
        {
            "type": "spotify",
            "id": "09x9v1o51dbqi5H0u7UGfp",
            "day_of_year": "10/15",
            "song": "I Will",
            "artist": "The Beatles",
            "note": ""
        },
        {
            "type": "spotify",
            "id": "5dS4r8s7z5r1LpivqrCP0U",
            "day_of_year": "10/16",
            "song": "Forever Mine",
            "artist": "Andra Day",
            "note": ""
        },
        {
            "type": "spotify",
            "id": "6PGoSes0D9eUDeeAafB2As",
            "day_of_year": "10/17",
            "song": "LOVE. ft. Zacari",
            "artist": "Kendrick Lamar",
            "note": ""
        },
        {
            "type": "spotify",
            "id": "5Ocoqiut683pC9mZFvncLz",
            "day_of_year": "10/18",
            "song": "Love Like Rockets",
            "artist": "Angels & Airwaves",
            "note": ""
        },
        {
            "type": "spotify",
            "id": "4TBBPZks71c60whhq0PgdP",
            "day_of_year": "10/19",
            "song": "(Your Love Keeps Lifting Me) Higher and Higher",
            "artist": "Jackie Wilson",
            "note": ""
        },
        {
            "type": "spotify",
            "id": "0d2iYfpKoM0QCKvcLCkBao",
            "day_of_year": "10/20",
            "song": "Eastside",
            "artist": "Benny Blanco, Halsey, & Khalid ",
            "note": ""
        },
        {
            "type": "spotify",
            "id": "1N883b1C3trjGcx2h4E99B",
            "day_of_year": "10/21",
            "song": "We're Going to Be Friends",
            "artist": "The White Stripes",
            "note": ""
        },
        {
            "type": "spotify",
            "id": "5uES1C2NgkdrNHiCwf9jRr",
            "day_of_year": "10/22",
            "song": "Baby Love",
            "artist": "The Supremes ",
            "note": ""
        },
        {
            "type": "spotify",
            "id": "0CaBBQsaAiRHhiLmzi7ZRp",
            "day_of_year": "10/23",
            "song": "Two Of Us",
            "artist": "The Beatles",
            "note": ""
        },
        {
            "type": "spotify",
            "id": "2ocDF2DDhIALebfIaGxBkF",
            "day_of_year": "10/24",
            "song": "Dreamlover",
            "artist": "Mariah Carey",
            "note": ""
        },
        {
            "type": "spotify",
            "id": "6JxxPhrbp3ZtQikOq19SyQ",
            "day_of_year": "10/25",
            "song": "Brand New Colony",
            "artist": "The Postal Service",
            "note": ""
        },
        {
            "type": "spotify",
            "id": "24SGws6o7m3TzROMO5Qc0g",
            "day_of_year": "10/26",
            "song": "Crazy Little Thing Called Love",
            "artist": "Queen",
            "note": ""
        },
        {
            "type": "spotify",
            "id": "0ESIjVxnDnCDaTPo6sStHm",
            "day_of_year": "10/27",
            "song": "Till There Was You",
            "artist": "The Beatles",
            "note": ""
        },
        {
            "type": "spotify",
            "id": "2tUBqZG2AbRi7Q0BIrVrEj",
            "day_of_year": "10/28",
            "song": "I Wanna Dance With Somebody (Who Loves Me)",
            "artist": "Whitney Houston",
            "note": ""
        },
        {
            "type": "spotify",
            "id": "3SdTKo2uVsxFblQjpScoHy",
            "day_of_year": "10/29",
            "song": "Stand By Me",
            "artist": "Ben E. King",
            "note": ""
        },
        {
            "type": "spotify",
            "id": "2UeFcWqBOuSpZbc0LLRsj9",
            "day_of_year": "10/30",
            "song": "I Love You So Much (It's Scary)",
            "artist": "Bob's Burgers",
            "note": ""
        },
        {
            "type": "spotify",
            "id": "1YwoYPfhuZlLDbJUH1cKSi",
            "day_of_year": "10/31",
            "song": "I Put A Spell On You",
            "artist": "Screamin' Jay Hawkins",
            "note": ""
        },
        {
            "type": "spotify",
            "id": "57M3x7GWQHGbaI6NgjWwr6",
            "day_of_year": "11/01",
            "song": "Washing Dishes",
            "artist": "Jack Johnson",
            "note": ""
        },
        {
            "type": "spotify",
            "id": "075rqIE8gmoigDH7N8rlaz",
            "day_of_year": "11/02",
            "song": "Here Comes My Girl",
            "artist": "Tom Petty",
            "note": ""
        },
        {
            "type": "spotify",
            "id": "0gd50I2gKioJ59C827EdAY",
            "day_of_year": "11/03",
            "song": "I'm Happy Just To Dance With You",
            "artist": "The Beatles",
            "note": ""
        },
        {
            "type": "spotify",
            "id": "3oT6aHD66EiGD5SALrKfHV",
            "day_of_year": "11/04",
            "song": "Thank You",
            "artist": "Led Zeppelin",
            "note": "If the sun refused to shine<br>I would still be loving you<br>When mountains crumble to the sea<br>There will still be you and me"
        },
        {
            "type": "spotify",
            "id": "1wwJYym3pzBEtIFKeeimdm",
            "day_of_year": "11/05",
            "song": "My Best Friend",
            "artist": "Weezer",
            "note": ""
        },
        {
            "type": "spotify",
            "id": "1f4iVGDitHYMVBaoc9GXO2",
            "day_of_year": "11/06",
            "song": "Love Will Keep Us Together",
            "artist": "Captain and Tennille",
            "note": ""
        },
        {
            "type": "spotify",
            "id": "6GsP3uMCd0Dn5T37C93waZ",
            "day_of_year": "11/07",
            "song": "Sick Love",
            "artist": "Red Hot Chili Peppers",
            "note": "\"Got a heavy laugh for such a tiny girl\""
        },
        {
            "type": "spotify",
            "id": "1kMAfusz1FuLN5AgaJPd3x",
            "day_of_year": "11/08",
            "song": "Home",
            "artist": "She & Him",
            "note": ""
        },
        {
            "type": "spotify",
            "id": "1vrd6UOGamcKNGnSHJQlSt",
            "day_of_year": "11/09",
            "song": "Love Story",
            "artist": "Taylor Swift",
            "note": ""
        },
        {
            "type": "spotify",
            "id": "19lLzX7vt4BhrSOaHeRyn7",
            "day_of_year": "11/10",
            "song": "Crazy in Love",
            "artist": "Beyoncé featuring Jay-Z",
            "note": ""
        },
        {
            "type": "spotify",
            "id": "0pNeVovbiZHkulpGeOx1Gj",
            "day_of_year": "11/11",
            "song": "Something",
            "artist": "The Beatles",
            "note": ""
        },
        {
            "type": "spotify",
            "id": "4vfioWSgbZSVwsYtPS1a6s",
            "day_of_year": "11/12",
            "song": "Stuck on You",
            "artist": "Meiko",
            "note": ""
        },
        {
            "type": "spotify",
            "id": "29sY1Zgd4BXoVcoiVbiUXi",
            "day_of_year": "11/13",
            "song": "As I Was Saying",
            "artist": "Jack Johnson",
            "note": ""
        },
        {
            "type": "spotify",
            "id": "22mek4IiqubGD9ctzxc69s",
            "day_of_year": "11/14",
            "song": "How Deep Is Your Love",
            "artist": "Calvin Harris & Disciples",
            "note": ""
        },
        {
            "type": "spotify",
            "id": "03MOcbkkoNLjP0G91iODSB",
            "day_of_year": "11/15",
            "song": "Quando, Quando, Quando",
            "artist": "Englebert Humperdinck",
            "note": ""
        },
        {
            "type": "spotify",
            "id": "75lw5aYrDq0TJsbkqCPRIJ",
            "day_of_year": "11/16",
            "song": "Rock & Roll Queen",
            "artist": "The Subways",
            "note": ""
        },
        {
            "type": "spotify",
            "id": "0CZQNI3Evb4Nd8GeU49LFj",
            "day_of_year": "11/17",
            "song": "C'mon Girl",
            "artist": "Red Hot Chili Peppers",
            "note": ""
        },
        {
            "type": "spotify",
            "id": "0oEyXbHhtUBqKdKHewG8Cn",
            "day_of_year": "11/18",
            "song": "The Dress Looks Nice on You",
            "artist": "Sufjan Stevens",
            "note": ""
        },
        {
            "type": "spotify",
            "id": "3vY7cKuKNY1oAsyVVn7AQz",
            "day_of_year": "11/19",
            "song": "La La Love You",
            "artist": "Pixies",
            "note": ""
        },
        {
            "type": "spotify",
            "id": "1euKWJfJSfPhgSendPrcXb",
            "day_of_year": "11/20",
            "song": "From Me to You",
            "artist": "The Beatles",
            "note": ""
        },
        {
            "type": "spotify",
            "id": "0FvB7aL3hJEy1s2LI7U09i",
            "day_of_year": "11/21",
            "song": "True Love Will Find You In The End",
            "artist": "Beck",
            "note": ""
        },
        {
            "type": "spotify",
            "id": "575NJxNUVDqwJGdzBrlLbv",
            "day_of_year": "11/22",
            "song": "Lost in Japan",
            "artist": "Shawn Mendes, Zedd",
            "note": ""
        },
        {
            "type": "spotify",
            "id": "0CokSRCu5hZgPxcZBaEzVE",
            "day_of_year": "11/23",
            "song": "Glorious",
            "artist": "Macklemore feat. Skylar Grey",
            "note": "You are Glorious!"
        },
        {
            "type": "spotify",
            "id": "0suLngfo7rJoetk7Ub6N8l",
            "day_of_year": "11/24",
            "song": "Octopus's Garden",
            "artist": "The Beatles",
            "note": ""
        },
        {
            "type": "spotify",
            "id": "1j0KabI4ajLZqRYgK6k4PQ",
            "day_of_year": "11/25",
            "song": "Be Still My Heart",
            "artist": "The Postal Service",
            "note": ""
        },
        {
            "type": "spotify",
            "id": "3GGg9FWBlAjrAvC16kazer",
            "day_of_year": "11/26",
            "song": "Lovesick",
            "artist": "Mura Masa",
            "note": ""
        },
        {
            "type": "spotify",
            "id": "5KIeVlKSb3kyVyfqzxTiMD",
            "day_of_year": "11/27",
            "song": "Never Far Away",
            "artist": "Chris Cornell",
            "note": ""
        },
        {
            "type": "spotify",
            "id": "7HTH1ppjkkOe7RLoBDKXYJ",
            "day_of_year": "11/28",
            "song": "Good Day Sunshine",
            "artist": "The Beatles",
            "note": ""
        },
        {
            "type": "spotify",
            "id": "2G2YzndIA6jeWFPBXhUjh5",
            "day_of_year": "11/29",
            "song": "Be My Baby",
            "artist": "The Ronettes",
            "note": ""
        },
        {
            "type": "spotify",
            "id": "0Q3W3sL8H56NLDOiwLAhO5",
            "day_of_year": "11/30",
            "song": "Transatlanticism",
            "artist": "Death Cab for Cutie",
            "note": "I need you so much closer."
        },
        {
            "type": "spotify",
            "id": "0shGCs5AkhwJIgUb0SSz2B",
            "day_of_year": "12/01",
            "song": "The Way You Look Tonight",
            "artist": "Frank Sinatra",
            "note": ""
        },
        {
            "type": "spotify",
            "id": "0voUr8lubIafUVJlauJxYF",
            "day_of_year": "12/02",
            "song": "Things We Said Today",
            "artist": "The Beatles",
            "note": ""
        },
        {
            "type": "spotify",
            "id": "5WjDmjD39LsFCRRALhorjd",
            "day_of_year": "12/03",
            "song": "I Got You",
            "artist": "Jack Johnson",
            "note": ""
        },
        {
            "type": "spotify",
            "id": "6PL6yZwoD7ZmlDczujaYPY",
            "day_of_year": "12/04",
            "song": "Higher Ground",
            "artist": "ODESZA, Naomi Wild",
            "note": ""
        },
        {
            "type": "spotify",
            "id": "6IwKcFdiRQZOWeYNhUiWIv",
            "day_of_year": "12/05",
            "song": "No One",
            "artist": "Alicia Keys",
            "note": ""
        },
        {
            "type": "spotify",
            "id": "2ydUT1pFhuLDnouelIv4WH",
            "day_of_year": "12/06",
            "song": "The Rock Show",
            "artist": "Blink-182",
            "note": ""
        },
        {
            "type": "spotify",
            "id": "1gFNm7cXfG1vSMcxPpSxec",
            "day_of_year": "12/07",
            "song": "Ob-La-Di, Ob-La-Da",
            "artist": "The Beatles",
            "note": ""
        },
        {
            "type": "spotify",
            "id": "1vlzSY7AttAiAvSEe1JbVs",
            "day_of_year": "12/08",
            "song": "Crush On You",
            "artist": "Elijah Who",
            "note": ""
        },
        {
            "type": "spotify",
            "id": "56SkdBKyR2zOkjk6wVFI9s",
            "day_of_year": "12/09",
            "song": "Possum Kingdom",
            "artist": "The Toadies",
            "note": "\"I want you for mine<br>My blushing bride<br>My lover, be my lover, yeah\""
        },
        {
            "type": "spotify",
            "id": "5qStOHXvQShPh8ijBKTsuM",
            "day_of_year": "12/10",
            "song": "By Your Side",
            "artist": "Beachwood Sparks",
            "note": ""
        },
        {
            "type": "spotify",
            "id": "2h9ryHBPwEGlZoo5iQ7Efj",
            "day_of_year": "12/11",
            "song": "Cupid",
            "artist": "Jack Johnson",
            "note": ""
        },
        {
            "type": "spotify",
            "id": "0tgVpDi06FyKpA1z0VMD4v",
            "day_of_year": "12/12",
            "song": "Perfect",
            "artist": "Ed Sheeran",
            "note": ""
        },
        {
            "type": "spotify",
            "id": "6nEkxYIEnrbYH7h1hJ8Xn6",
            "day_of_year": "12/13",
            "song": "She Loves You",
            "artist": "The Beatles",
            "note": ""
        },
        {
            "type": "spotify",
            "id": "5uCax9HTNlzGybIStD3vDh",
            "day_of_year": "12/14",
            "song": "Say You Won't Let Go",
            "artist": "James Athur",
            "note": ""
        },
        {
            "type": "spotify",
            "id": "0W4Kpfp1w2xkY3PrV714B7",
            "day_of_year": "12/15",
            "song": "Ho Hey",
            "artist": "The Lumineers",
            "note": ""
        },
        {
            "type": "spotify",
            "id": "25Yzff59UGjz7wNWmjM39h",
            "day_of_year": "12/16",
            "song": "Moondance",
            "artist": "Michael Bublé",
            "note": ""
        },
        {
            "type": "spotify",
            "id": "0itNMuBHye9fu392b4e9oa",
            "day_of_year": "12/17",
            "song": "Tell Me Baby",
            "artist": "Red Hot Chili Peppers",
            "note": ""
        },
        {
            "type": "spotify",
            "id": "6ETGYNhwtjUzD5sbxzNcT3",
            "day_of_year": "12/18",
            "song": "Snowfall",
            "artist": "Ingrid Michaelson",
            "note": ""
        },
        {
            "type": "spotify",
            "id": "2B4Y9u4ERAFiMo13XPJyGP",
            "day_of_year": "12/19",
            "song": "Here, There And Everywhere",
            "artist": "The Beatles",
            "note": ""
        },
        {
            "type": "spotify",
            "id": "5DbULoYNVa8Oo0wVXDggmy",
            "day_of_year": "12/20",
            "song": "Warm December",
            "artist": "Julie London",
            "note": ""
        },
        {
            "type": "spotify",
            "id": "4FPrAERfkPKOBKrRoyuxLu",
            "day_of_year": "12/21",
            "song": "Cold December Night",
            "artist": "Michael Bublé",
            "note": ""
        },
        {
            "type": "spotify",
            "id": "7inXu0Eaeg02VsM8kHNvzM",
            "day_of_year": "12/22",
            "song": "Let It Snow! Let It Snow! Let It Snow!",
            "artist": "Frank Sinatra",
            "note": ""
        },
        {
            "type": "spotify",
            "id": "0jgVkOMLMRZTgx06ddo4DQ",
            "day_of_year": "12/23",
            "song": "That's What I Want for Christmas",
            "artist": "Nancy Wilson ",
            "note": ""
        },
        {
            "type": "spotify",
            "id": "1j75fzIDImv5G7NvSW9FNK",
            "day_of_year": "12/24",
            "song": "All I Want For Christmas Is You",
            "artist": "She & Him",
            "note": ""
        },
        {
            "type": "spotify",
            "id": "3Ty1I3nJy6uxSVF41XvnMl",
            "day_of_year": "12/25",
            "song": "Christmas Everyday",
            "artist": "Smokey Robinson & The Miracles",
            "note": ""
        },
        {
            "type": "spotify",
            "id": "3fMbBYxJrFX6HxPILnzQaf",
            "day_of_year": "12/26",
            "song": "A Marshmallow World",
            "artist": "She & Him",
            "note": ""
        },
        {
            "type": "spotify",
            "id": "6koowTu9pFHPEcZnACLKbK",
            "day_of_year": "12/27",
            "song": "Brown Skin Girl",
            "artist": "Leon Bridges",
            "note": ""
        },
        {
            "type": "spotify",
            "id": "0IktbUcnAGrvD03AWnz3Q8",
            "day_of_year": "12/28",
            "song": "Lucky",
            "artist": "Jason Mraz, Colbie Caillat",
            "note": ""
        },
        {
            "type": "spotify",
            "id": "0VaIsQoIQY10uxBrOyZ5cQ",
            "day_of_year": "12/29",
            "song": "May I Have This Dance (Remix)",
            "artist": "Francis and the Lights",
            "note": ""
        },
        {
            "type": "spotify",
            "id": "2aibwv5hGXSgw7Yru8IYTO",
            "day_of_year": "12/30",
            "song": "Snow (Hey Oh)",
            "artist": "Red Hot Chili Peppers",
            "note": ""
        },
        {
            "type": "spotify",
            "id": "0SZim5k1ypcgRsWmFcrGfs",
            "day_of_year": "12/31",
            "song": "What Are You Doing New Year’s Eve?",
            "artist": "The Head and The Heart",
            "note": ""
        },
        {
            "type": "spotify",
            "id": "1EZJBB6bvCcrvYRlOyoHuf",
            "day_of_year": "01/01",
            "song": "Do You Remember",
            "artist": "Jack Johnson",
            "note": ""
        },
        {
            "type": "spotify",
            "id": "2CxTkdvhDuQrOxl8xXkdJS",
            "day_of_year": "01/02",
            "song": "Every Little Thing",
            "artist": "The Beatles",
            "note": ""
        },
        {
            "type": "spotify",
            "id": "6FKU84JHM1lbiy5Dx0Dyqd",
            "day_of_year": "01/03",
            "song": "The Joker",
            "artist": "Steve Miller Band",
            "note": "You're the cutest thing that I ever did see"
        },
        {
            "type": "spotify",
            "id": "2dEVAvwPAJrWFErXxREGVX",
            "day_of_year": "01/04",
            "song": "Eres tú",
            "artist": "Carla Morrison",
            "note": ""
        },
        {
            "type": "spotify",
            "id": "6squXSZ3rl7tENdZiOuIEj",
            "day_of_year": "01/05",
            "song": "Here In My Arms",
            "artist": "Leon Bridges",
            "note": ""
        },
        {
            "type": "spotify",
            "id": "51l8jiqsGYCiKUJBLXJvA9",
            "day_of_year": "01/06",
            "song": "Stay With You",
            "artist": "John Legend",
            "note": ""
        },
        {
            "type": "spotify",
            "id": "6jeWgaprnGyAsRhUcNuZKX",
            "day_of_year": "01/07",
            "song": "Toothpaste Kisses",
            "artist": "The Maccabees",
            "note": ""
        },
        {
            "type": "spotify",
            "id": "1ndGB6rvxKYN9seCYO1dTF",
            "day_of_year": "01/08",
            "song": "The Zephyr Song",
            "artist": "Red Hot Chili Peppers",
            "note": ""
        },
        {
            "type": "spotify",
            "id": "4dIPtEnmudhZPD8MsAtzSK",
            "day_of_year": "01/09",
            "song": "Two Punks In Love",
            "artist": "bülow",
            "note": ""
        },
        {
            "type": "spotify",
            "id": "0YkbYk24ODhuewb79zZZzM",
            "day_of_year": "01/10",
            "song": "You Wreck Me",
            "artist": "Tom Petty",
            "note": ""
        },
        {
            "type": "spotify",
            "id": "1YLJVmuzeM2YSUkCCaTNUB",
            "day_of_year": "01/11",
            "song": "Dog Days Are Over",
            "artist": "Florence + The Machine",
            "note": ""
        },
        {
            "type": "spotify",
            "id": "7EUfNvyCVxQV3oN5ScA2Lb",
            "day_of_year": "01/12",
            "song": "Next To Me",
            "artist": "Imagine Dragons",
            "note": ""
        },
        {
            "type": "spotify",
            "id": "79nGvSoOQr3WHK3Y96Qt0u",
            "day_of_year": "01/13",
            "song": "Home",
            "artist": "Jack Johnson",
            "note": ""
        },
        {
            "type": "spotify",
            "id": "7HSNDCmILAqYrMZh4tZgp4",
            "day_of_year": "01/14",
            "song": "Found You",
            "artist": "Kasbo, Chelsea Cutler",
            "note": ""
        },
        {
            "type": "spotify",
            "id": "5JEx7HbmvHQQswJCsoo9rA",
            "day_of_year": "01/15",
            "song": "Close To Me",
            "artist": "Ellie Goulding",
            "note": ""
        },
        {
            "type": "spotify",
            "id": "1uGwCbelG6h8hdcCPFSN1Z",
            "day_of_year": "01/16",
            "song": "I'm so in Love with You",
            "artist": "Jill Andrews, Seth Avett",
            "note": ""
        },
        {
            "type": "spotify",
            "id": "2jnr9KaaMAmvk0zMcM9UzV",
            "day_of_year": "01/17",
            "song": "Tell Me What You See",
            "artist": "The Beatles",
            "note": ""
        },
        {
            "type": "spotify",
            "id": "5EA06TsQmqmQXZiEhr1AaM",
            "day_of_year": "01/18",
            "song": "Coming Home",
            "artist": "Leon Bridges",
            "note": ""
        },
        {
            "type": "spotify",
            "id": "3mKQ7eTxsgT8EcTuLBXxUu",
            "day_of_year": "01/19",
            "song": "Turn Around",
            "artist": "The Postal Service",
            "note": ""
        },
        {
            "type": "spotify",
            "id": "2YlZnw2ikdb837oKMKjBkW",
            "day_of_year": "01/20",
            "song": "Like I'm Gonna Lose You",
            "artist": "Meghan Trainor, John Legend",
            "note": ""
        },
        {
            "type": "spotify",
            "id": "2I8OSnbWSkg0ntiU5cXp0G",
            "day_of_year": "01/21",
            "song": "From The Clouds",
            "artist": "Jack Johnson",
            "note": ""
        },
        {
            "type": "spotify",
            "id": "34ceTg8ChN5HjrqiIYCn9Q",
            "day_of_year": "01/22",
            "song": "Miss Independent",
            "artist": "Ne-Yo",
            "note": ""
        },
        {
            "type": "spotify",
            "id": "2kerqZxEIfdGlMy6BxseFy",
            "day_of_year": "01/23",
            "song": "Prom Night",
            "artist": "Anamanaguchi",
            "note": ""
        },
        {
            "type": "spotify",
            "id": "6YK2tAEYnHgYkkC6TSziqM",
            "day_of_year": "01/24",
            "song": "Fell in Love with a Girl",
            "artist": "The White Stripes",
            "note": ""
        },
        {
            "type": "spotify",
            "id": "1kCewNSs909Xj1naXr36X8",
            "day_of_year": "01/25",
            "song": "Amor Prohibido",
            "artist": "Selena",
            "note": ""
        },
        {
            "type": "spotify",
            "id": "2RvKsA6Ho7VbJkVFiD4UQF",
            "day_of_year": "01/26",
            "song": "Hold Me Tight",
            "artist": "The Beatles",
            "note": ""
        },
        {
            "type": "spotify",
            "id": "68vgtRHr7iZHpzGpon6Jlo",
            "day_of_year": "01/27",
            "song": "My Boo",
            "artist": "Usher, Alicia Keys",
            "note": ""
        },
        {
            "type": "spotify",
            "id": "05SBRd4fXgn8FX7bf8BCAE",
            "day_of_year": "01/28",
            "song": "I Need Your Love",
            "artist": "Calvin Harris, Ellie Goulding",
            "note": ""
        },
        {
            "type": "spotify",
            "id": "6y75sFXhHlZJ2N5UVaUBN9",
            "day_of_year": "01/29",
            "song": "God's Child (Baila Conmigo)",
            "artist": "Selena",
            "note": ""
        },
        {
            "type": "spotify",
            "id": "7FNFX9sTKfXqfiir5OWKmY",
            "day_of_year": "01/30",
            "song": "Earned It",
            "artist": "The Weeknd",
            "note": ""
        },
        {
            "type": "spotify",
            "id": "5bC4y9Zhn6ng0MOzACCHkc",
            "day_of_year": "01/31",
            "song": "For Your Love",
            "artist": "The Yardbirds",
            "note": ""
        },
        {
            "type": "spotify",
            "id": "60wwxj6Dd9NJlirf84wr2c",
            "day_of_year": "02/01",
            "song": "Clarity",
            "artist": "Zedd, Foxes",
            "note": ""
        },
        {
            "type": "spotify",
            "id": "5esPpmrM2AsyDVgOKzWQwU",
            "day_of_year": "02/02",
            "song": "Beyond",
            "artist": "Leon Bridges",
            "note": ""
        },
        {
            "type": "spotify",
            "id": "4esOae7i4rqTbAu9o5Pxco",
            "day_of_year": "02/03",
            "song": "Girl On Fire",
            "artist": "Alicia Keys",
            "note": ""
        },
        {
            "type": "spotify",
            "id": "2ue1KRstSKHF8jQkIJZiNC",
            "day_of_year": "02/04",
            "song": "It's Only Love",
            "artist": "The Beatles",
            "note": ""
        },
        {
            "type": "spotify",
            "id": "6AvNWGcB6Ld6B46cbyE8oP",
            "day_of_year": "02/05",
            "song": "Teach Me Tonight",
            "artist": "She & Him",
            "note": ""
        },
        {
            "type": "spotify",
            "id": "3V5vrRmjNj4MssxW8cEJov",
            "day_of_year": "02/06",
            "song": "How Sweet It Is (To Be Loved By You)",
            "artist": "Marvin Gaye",
            "note": ""
        },
        {
            "type": "spotify",
            "id": "5RLzsVW6UNiV2YrOlKwzNN",
            "day_of_year": "02/07",
            "song": "Blue Moon",
            "artist": "Frank Sinatra",
            "note": ""
        },
        {
            "type": "spotify",
            "id": "08iEcssxfzwkkDU3Ec6rLI",
            "day_of_year": "02/08",
            "song": "Always Mine",
            "artist": "Selena",
            "note": ""
        },
        {
            "type": "spotify",
            "id": "4I4aQGNJ2HufloNtB65nxR",
            "day_of_year": "02/09",
            "song": "That's Amore",
            "artist": "Dean Martin",
            "note": ""
        },
        {
            "type": "spotify",
            "id": "5QPc3SVA8TAeA5NpXXtqAa",
            "day_of_year": "02/10",
            "song": "Dreaming",
            "artist": "Seapony",
            "note": ""
        },
        {
            "type": "spotify",
            "id": "0r7BdcooOV4XbG5IM14YUa",
            "day_of_year": "02/11",
            "song": "Promise What You Will",
            "artist": "Iron & Wine",
            "note": ""
        },
        {
            "type": "spotify",
            "id": "3KiexfmhxHvG5IgAElmTkd",
            "day_of_year": "02/12",
            "song": "I Saw Her Standing There",
            "artist": "The Beatles",
            "note": ""
        },
        {
            "type": "spotify",
            "id": "1Y6DGcTCuMAtw8KB3h4W3q",
            "day_of_year": "02/13",
            "song": "Around The World",
            "artist": "Red Hot Chili Peppers",
            "note": ""
        },
        {
            "type": "spotify",
            "id": "2uRz1DAgAuK7CObjr1Lepu",
            "day_of_year": "02/14",
            "song": "Never Fade",
            "artist": "Jack Johnson",
            "note": ""
        },
        {
            "type": "spotify",
            "id": "3KxOYNt66Hj42HzO7ao0CV",
            "day_of_year": "02/15",
            "song": "Happy Together",
            "artist": "Weezer",
            "note": ""
        },
        {
            "type": "spotify",
            "id": "0736w0GUZoRcKXXx3oyirg",
            "day_of_year": "02/16",
            "song": "Built to Last",
            "artist": "Tom Petty",
            "note": ""
        },
        {
            "type": "spotify",
            "id": "7J41dYQolQJEtj3UmKLu5r",
            "day_of_year": "02/17",
            "song": "U Got It Bad",
            "artist": "Usher",
            "note": ""
        },
        {
            "type": "spotify",
            "id": "1JHV2dXwi7A3ujQxCWNrm6",
            "day_of_year": "02/18",
            "song": "Amame, Quiereme",
            "artist": "Selena",
            "note": ""
        },
        {
            "type": "spotify",
            "id": "41yIvlFgvGwxq8qTqAR7eG",
            "day_of_year": "02/19",
            "song": "Bloom",
            "artist": "The Paper Kites",
            "note": ""
        },
        {
            "type": "spotify",
            "id": "4NEAoEh4hZF1Tgp1QXrUHC",
            "day_of_year": "02/20",
            "song": "Heart Beat Here",
            "artist": "Dashboard Confessional",
            "note": ""
        },
        {
            "type": "spotify",
            "id": "2UgmULNYP8iHNmKTn45vnt",
            "day_of_year": "02/21",
            "song": "Even Fairy Tale Characters Would Be Jealous",
            "artist": "PlayRadioPlay!",
            "note": ""
        },
        {
            "type": "spotify",
            "id": "4eTVpfb9fISH1FV4APpX2T",
            "day_of_year": "02/22",
            "song": "You & Me (Flume Remix)",
            "artist": "Disclosure",
            "note": ""
        },
        {
            "type": "spotify",
            "id": "6vt0I1cw1YmAIKDJvHVIM5",
            "day_of_year": "02/23",
            "song": "Suit & Tie",
            "artist": "Justin Timberlake, JAY Z",
            "note": ""
        },
        {
            "type": "spotify",
            "id": "7LP4Es66zdY7CyjepqmvAg",
            "day_of_year": "02/24",
            "song": "Down",
            "artist": "Jay Sean, Lil Wayne",
            "note": ""
        },
        {
            "type": "spotify",
            "id": "4sG6J4S2FCuMr3oooYAwFS",
            "day_of_year": "02/25",
            "song": "Astronaut (Something About Your Love)",
            "artist": "Mansionair",
            "note": ""
        },
        {
            "type": "spotify",
            "id": "1IAzD1muglOxOcPbUHs70R",
            "day_of_year": "02/26",
            "song": "Whatever You Like",
            "artist": "T.I.",
            "note": ""
        },
        {
            "type": "spotify",
            "id": "3tGhRLgcCP6SIZU3tbGl7l",
            "day_of_year": "02/27",
            "song": "Got To Get You Into My Life",
            "artist": "The Beatles",
            "note": ""
        },
        {
            "type": "spotify",
            "id": "5jE2zX35pwQIXPYkdDY1gL",
            "day_of_year": "02/28",
            "song": "Hannah",
            "artist": "Freelance Whales",
            "note": ""
        },
        {
            "type": "spotify",
            "id": "1dGr1c8CrMLDpV6mPbImSI",
            "day_of_year": "02/29",
            "song": "Lover",
            "artist": "Taylor Swift",
            "note": "\"Can I go where you go?\""
        },
        {
            "type": "spotify",
            "id": "03uFeLfjTtzA8dpnkMr76W",
            "day_of_year": "03/01",
            "song": "Love and Some Verses",
            "artist": "Iron & Wine",
            "note": ""
        },
        {
            "type": "spotify",
            "id": "1ejlhx6DYlsr8ch5XpZp9i",
            "day_of_year": "03/02",
            "song": "It's Always You",
            "artist": "She & Him",
            "note": ""
        },
        {
            "type": "spotify",
            "id": "1OxqCSTvWrCwoS413r9xel",
            "day_of_year": "03/03",
            "song": "I'm Getting Used To You",
            "artist": "Selena",
            "note": ""
        },
        {
            "type": "spotify",
            "id": "3TgJ1kDhIOFcstAhfu531J",
            "day_of_year": "03/04",
            "song": "Swing Life Away",
            "artist": "Rise Against",
            "note": ""
        },
        {
            "type": "spotify",
            "id": "6CDiKAFgbWXlwQTU59GKYT",
            "day_of_year": "03/05",
            "song": "Kiss The Girl",
            "artist": "Samuel E. Wright",
            "note": ""
        },
        {
            "type": "spotify",
            "id": "2vO1wr5wIEHqQmY4jWbuhi",
            "day_of_year": "03/06",
            "song": "Angel",
            "artist": "Jack Johnson",
            "note": ""
        },
        {
            "type": "spotify",
            "id": "76ati4YtRJe4vkpcL5VFy5",
            "day_of_year": "03/07",
            "song": "Never Knew I Needed",
            "artist": "Ne-Yo",
            "note": ""
        },
        {
            "type": "spotify",
            "id": "3Z25k4ZF6QENy2d9YatsM5",
            "day_of_year": "03/08",
            "song": "I Want You (She's So Heavy)",
            "artist": "The Beatles",
            "note": ""
        },
        {
            "type": "spotify",
            "id": "4lO6SXuPhhrYAHTSS7eFH4",
            "day_of_year": "03/09",
            "song": "So Long",
            "artist": "Zooey Deschanel, M. Ward",
            "note": ""
        },
        {
            "type": "spotify",
            "id": "1zp6nac2R9OT9pV5UJA3jo",
            "day_of_year": "03/10",
            "song": "Ven Conmigo",
            "artist": "Selena",
            "note": ""
        },
        {
            "type": "spotify",
            "id": "3ERa3mEeOnrh2Mc47qM6T1",
            "day_of_year": "03/11",
            "song": "Halo",
            "artist": "Beyoncé",
            "note": ""
        },
        {
            "type": "spotify",
            "id": "7z0JDE4w67HXt5lEWsU2Hj",
            "day_of_year": "03/12",
            "song": "Strawberry Bubblegum",
            "artist": "Justin Timberlake",
            "note": ""
        },
        {
            "type": "spotify",
            "id": "42qkSeX6HNJYHxlk6cWoFe",
            "day_of_year": "03/13",
            "song": "Words Of Love",
            "artist": "The Beatles",
            "note": ""
        },
        {
            "type": "spotify",
            "id": "11bD1JtSjlIgKgZG2134DZ",
            "day_of_year": "03/14",
            "song": "Chasing Cars",
            "artist": "Snow Patrol",
            "note": ""
        },
        {
            "type": "spotify",
            "id": "5E8yddtSG3sH4hw2SfwcgW",
            "day_of_year": "03/15",
            "song": "Can You Feel The Love Tonight",
            "artist": "Nathan Lane, Joseph Williams, Ernie Sabella, Sally Dworsky, Kristle Edwards",
            "note": ""
        },
        {
            "type": "spotify",
            "id": "34gCuhDGsG4bRPIf9bb02f",
            "day_of_year": "03/16",
            "song": "Thinking Out Loud",
            "artist": "Ed Sheeran",
            "note": ""
        },
        {
            "type": "spotify",
            "id": "1FwlOJvpcuYN6Sj3qo070C",
            "day_of_year": "03/17",
            "song": "I Say A Little Prayer",
            "artist": "Aretha Franklin",
            "note": ""
        },
        {
            "type": "spotify",
            "id": "7rqtOP0O0DL6P1wgsMW2uX",
            "day_of_year": "03/18",
            "song": "Lion's Mane",
            "artist": "Iron & Wine",
            "note": ""
        },
        {
            "type": "spotify",
            "id": "4GBaPHvAyj4V2jeobD9tsy",
            "day_of_year": "03/19",
            "song": "The Word",
            "artist": "The Beatles",
            "note": ""
        },
        {
            "type": "spotify",
            "id": "2XWjPtKdi5sucFYtVav07d",
            "day_of_year": "03/20",
            "song": "365",
            "artist": "Zedd, Katy Perry",
            "note": ""
        },
        {
            "type": "spotify",
            "id": "1Y0iQblBDaw2qMutZqGoUH",
            "day_of_year": "03/21",
            "song": "My Love",
            "artist": "The Bird and The Bee",
            "note": ""
        },
        {
            "type": "spotify",
            "id": "4Hhv2vrOTy89HFRcjU3QOx",
            "day_of_year": "03/22",
            "song": "At Last",
            "artist": "Etta James",
            "note": ""
        },
        {
            "type": "spotify",
            "id": "6z5Yh7kOKeLjqIsNdokIpU",
            "day_of_year": "03/23",
            "song": "A Thousand Years",
            "artist": "Christina Perri",
            "note": ""
        },
        {
            "type": "spotify",
            "id": "1l2WkPJeLEuQtBzp0DMuMX",
            "day_of_year": "03/24",
            "song": "Adore",
            "artist": "Amy Shark",
            "note": ""
        },
        {
            "type": "spotify",
            "id": "0Qw7qGuXlVBZLcfoQ17yZn",
            "day_of_year": "03/25",
            "song": "Old Pine",
            "artist": "Ben Howard",
            "note": ""
        },
        {
            "type": "spotify",
            "id": "2urMIG2y7CsnH206CxykV0",
            "day_of_year": "03/26",
            "song": "Once Upon A Dream",
            "artist": "Mary Costa, Bill Shirley, \"Sleeping Beauty\" Chorus",
            "note": ""
        },
        {
            "type": "spotify",
            "id": "37kTASujIfZZ27NV7PfIrf",
            "day_of_year": "03/27",
            "song": "Hard To Concentrate",
            "artist": "Red Hot Chili Peppers",
            "note": "All I want is for you to be happy and<br>Take this woman and make you my family and<br>Finally you have found someone perfect and<br>Finally you have found... now"
        },
        {
            "type": "spotify",
            "id": "1k1Bqnv2R0uJXQN4u6LKYt",
            "day_of_year": "03/28",
            "song": "Ain't No Sunshine",
            "artist": "Bill Withers",
            "note": ""
        },
        {
            "type": "spotify",
            "id": "0PpZijLwoROXHsCgvBoNcf",
            "day_of_year": "03/29",
            "song": "Every Songbird Says",
            "artist": "Sam Beam & Jesca Hoop",
            "note": ""
        },
        {
            "type": "spotify",
            "id": "7BVwi9cIzSc6tpyxsp47vJ",
            "day_of_year": "03/30",
            "song": "Mess is Mine",
            "artist": "Vance Joy",
            "note": ""
        },
        {
            "type": "spotify",
            "id": "0PDCewmZCp0P5s00bptcdd",
            "day_of_year": "03/31",
            "song": "This Will Be",
            "artist": "Natalie Cole",
            "note": ""
        },
        {
            "type": "spotify",
            "id": "20GXVF6YKr4AUP3B0m3g8v",
            "day_of_year": "04/01",
            "song": "Dulce Amor",
            "artist": "Selena",
            "note": ""
        },
        {
            "type": "spotify",
            "id": "4oLQ0imA5IDtNUnhFKY87q",
            "day_of_year": "04/02",
            "song": "When I Get Home",
            "artist": "The Beatles",
            "note": ""
        },
        {
            "type": "spotify",
            "id": "7nSP35TXXGW3fYlICWR8cx",
            "day_of_year": "04/03",
            "song": "Tomorrow Morning",
            "artist": "Jack Johnson",
            "note": ""
        },
        {
            "type": "spotify",
            "id": "3TCauNPqFiniaYHBvEVoHG",
            "day_of_year": "04/04",
            "song": "Beautiful",
            "artist": "Christina Aguilera",
            "note": ""
        },
        {
            "type": "spotify",
            "id": "7JJmb5XwzOO8jgpou264Ml",
            "day_of_year": "04/05",
            "song": "There's Nothing Holdin' Me Back",
            "artist": "Shawn Mendes",
            "note": ""
        },
        {
            "type": "spotify",
            "id": "7GqWnsKhMtEW0nzki5o0d8",
            "day_of_year": "04/06",
            "song": "Killer Queen",
            "artist": "Queen",
            "note": ""
        },
        {
            "type": "spotify",
            "id": "62NVyyEBiRxGae3SeB97nl",
            "day_of_year": "04/07",
            "song": "Stay With Me",
            "artist": "Sam Smith",
            "note": ""
        },
        {
            "type": "spotify",
            "id": "3zHq9ouUJQFQRf3cm1rRLu",
            "day_of_year": "04/08",
            "song": "Love Me Like You Do",
            "artist": "Ellie Goulding",
            "note": ""
        },
        {
            "type": "spotify",
            "id": "39badcyKTjOtBvv4aywpfs",
            "day_of_year": "04/09",
            "song": "Universally Speaking",
            "artist": "Red Hot Chili Peppers",
            "note": "\"Simply put I saw your love stream flow\""
        },
        {
            "type": "spotify",
            "id": "7iocNjLrxPHLl8njgRlv5U",
            "day_of_year": "04/10",
            "song": "Married Life",
            "artist": "Michael Giacchino",
            "note": ""
        },
        {
            "type": "spotify",
            "id": "4CfYxSs4Dr8KWORCmN3hom",
            "day_of_year": "04/11",
            "song": "That Girl",
            "artist": "Justin Timberlake",
            "note": ""
        },
        {
            "type": "spotify",
            "id": "7pOWWGpUc3T05IXfymgIP3",
            "day_of_year": "04/12",
            "song": "This Magic Moment",
            "artist": "The Drifters",
            "note": ""
        },
        {
            "type": "spotify",
            "id": "3ekNuTF3UpOvIZCfiejpnC",
            "day_of_year": "04/13",
            "song": "Stubborn Love",
            "artist": "The Lumineers",
            "note": ""
        },
        {
            "type": "spotify",
            "id": "4RdJFhfLQcezwN5LsXl4qP",
            "day_of_year": "04/14",
            "song": "Love You To",
            "artist": "The Beatles",
            "note": ""
        },
        {
            "type": "spotify",
            "id": "3OltYYcLZUhvho5QoRbUNr",
            "day_of_year": "04/15",
            "song": "Accidentally in Love",
            "artist": "Counting Crows",
            "note": ""
        },
        {
            "type": "spotify",
            "id": "77enz5hl8RicxrbPB56VXQ",
            "day_of_year": "04/16",
            "song": "I Will Spend My Whole Life Loving You",
            "artist": "Kina Grannis, Imaginary Future",
            "note": ""
        },
        {
            "type": "spotify",
            "id": "6RUKPb4LETWmmr3iAEQktW",
            "day_of_year": "04/17",
            "song": "Something Just Like This",
            "artist": "Coldplay, The Chainsmokers",
            "note": ""
        },
        {
            "type": "spotify",
            "id": "6WVHotTBHCfpWaBD14sEkC",
            "day_of_year": "04/18",
            "song": "I'M DOWN",
            "artist": "Meghan Trainor",
            "note": ""
        },
        {
            "type": "spotify",
            "id": "6FRePTC2w57kLtE4rg20N1",
            "day_of_year": "04/19",
            "song": "Unchained Melody",
            "artist": "She & Him",
            "note": ""
        },
        {
            "type": "spotify",
            "id": "28fIB6jyKHx91jXd3CPX72",
            "day_of_year": "04/20",
            "song": "Quiero",
            "artist": "Selena",
            "note": ""
        },
        {
            "type": "spotify",
            "id": "2IssBpPtHcViZL5vYQNHhA",
            "day_of_year": "04/21",
            "song": "Like To Be You",
            "artist": "Shawn Mendes, Julia Michaels",
            "note": ""
        },
        {
            "type": "spotify",
            "id": "5icOoE6VgqFKohjWWNp0Ac",
            "day_of_year": "04/22",
            "song": "Here With Me",
            "artist": "Marshmello ft. CHVRCHES",
            "note": ""
        },
        {
            "type": "spotify",
            "id": "2yXSduJwEJH0HpyVMavzus",
            "day_of_year": "04/23",
            "song": "Same Girl",
            "artist": "Jack Johnson",
            "note": ""
        },
        {
            "type": "spotify",
            "id": "00Fm2c5jzqOncpbIn5AKzL",
            "day_of_year": "04/24",
            "song": "Be Near You",
            "artist": "Nojon",
            "note": ""
        },
        {
            "type": "spotify",
            "id": "5OyJgKz7cGxjEZbCfjzTb7",
            "day_of_year": "04/25",
            "song": "an Older Couple Holding Hands",
            "artist": "Lullatone",
            "note": ""
        },
        {
            "type": "spotify",
            "id": "5dpRJkvY8oWMQmQbEQTXhO",
            "day_of_year": "04/26",
            "song": "For You Blue",
            "artist": "The Beatles",
            "note": ""
        },
        {
            "type": "spotify",
            "id": "6wR1c5Dv5PI3sXmC3ZwJPk",
            "day_of_year": "04/27",
            "song": "Stuck With Me",
            "artist": "Timeflies",
            "note": ""
        },
        {
            "type": "spotify",
            "id": "2uQNcZYa0SEbfW4cj0d9OS",
            "day_of_year": "04/28",
            "song": "I Like Me Better",
            "artist": "Lauv",
            "note": ""
        },
        {
            "type": "spotify",
            "id": "6EfXW7sXZcr2X2bGHNHBAA",
            "day_of_year": "04/29",
            "song": "Coming Home",
            "artist": "Seven Lions, Mike Mains",
            "note": ""
        },
        {
            "type": "spotify",
            "id": "4wLfRv7Og2J02JLayZIYph",
            "day_of_year": "04/30",
            "song": "Some Kind of Magic",
            "artist": "LVTHER, Myzica",
            "note": ""
        },
        {
            "type": "spotify",
            "id": "5J2CHimS7dWYMImCHkEFaJ",
            "day_of_year": "05/01",
            "song": "A Hard Day's Night",
            "artist": "The Beatles",
            "note": ""
        },
        {
            "type": "spotify",
            "id": "7xhvCzIguRfyfQyGrnWuVn",
            "day_of_year": "05/02",
            "song": "Low Key",
            "artist": "Ally Brooke, Tyga",
            "note": ""
        },
        {
            "type": "spotify",
            "id": "3oP2vxUR2bjFCrU9YolGnM",
            "day_of_year": "05/03",
            "song": "I Could Die For You",
            "artist": "Red Hot Chili Peppers",
            "note": ""
        },
        {
            "type": "spotify",
            "id": "0mqTcM8kuu2IYPotMt7AzS",
            "day_of_year": "05/04",
            "song": "Make You Feel My Love",
            "artist": "Adele ",
            "note": ""
        },
        {
            "type": "spotify",
            "id": "6G41H0Zd0kQ1WXWDoEotoJ",
            "day_of_year": "05/05",
            "song": "Time After Time",
            "artist": "Cyndi Lauper",
            "note": ""
        },
        {
            "type": "spotify",
            "id": "5tztLBvTlNC15Np2tnQ5Ll",
            "day_of_year": "05/06",
            "song": "All I've Got To Do",
            "artist": "The Beatles",
            "note": ""
        },
        {
            "type": "spotify",
            "id": "3eHbKczzbh0zH5olpTgfW8",
            "day_of_year": "05/07",
            "song": "Enamorada De Ti",
            "artist": "Selena",
            "note": ""
        },
        {
            "type": "spotify",
            "id": "1lUdXbhl6u6QMQZRTAhlWW",
            "day_of_year": "05/08",
            "song": "Naked As We Came",
            "artist": "Iron & Wine",
            "note": ""
        },
        {
            "type": "spotify",
            "id": "3cVWNLd0uEHkc2tnBoE3Ay",
            "day_of_year": "05/09",
            "song": "Somethin' Stupid",
            "artist": "Frank Sinatra, Nancy Sinatra",
            "note": ""
        },
        {
            "type": "spotify",
            "id": "3eB9M6owEHwk4nNrZRNUwd",
            "day_of_year": "05/10",
            "song": "Mi Persona Favorita",
            "artist": "Alejandro Sanz feat. Camila Cabello",
            "note": ""
        },
        {
            "type": "spotify",
            "id": "2NcstvY8H9PVQ0DMNGHckh",
            "day_of_year": "05/11",
            "song": "America's Sweetheart",
            "artist": "Elle King",
            "note": "💪🏽"
        },
        {
            "type": "spotify",
            "id": "33mgh5V3qu50nnJAXQqfau",
            "day_of_year": "05/12",
            "song": "What You Thought You Need",
            "artist": "Jack Johnson",
            "note": "map emoji"
        },
        {
            "type": "spotify",
            "id": "5ZBeML7Lf3FMEVviTyvi8l",
            "day_of_year": "05/13",
            "song": "Twist And Shout",
            "artist": "The Beatles",
            "note": ""
        },
        {
            "type": "spotify",
            "id": "22i86sVWNjLu7fttP4gA02",
            "day_of_year": "05/14",
            "song": "Honeybee",
            "artist": "The Head and the Heart",
            "note": ""
        },
        {
            "type": "spotify",
            "id": "07NLq7udWxrL5pLZBVH1BW",
            "day_of_year": "05/15",
            "song": "I Was Made for You",
            "artist": "She & Him",
            "note": ""
        },
        {
            "type": "spotify",
            "id": "1dQOMZz9SkT7ig0w65lQWC",
            "day_of_year": "05/16",
            "song": "This Year's Love",
            "artist": "David Gray",
            "note": ""
        },
        {
            "type": "spotify",
            "id": "69uxyAqqPIsUyTO8txoP2M",
            "day_of_year": "05/17",
            "song": "Adventure of a Lifetime",
            "artist": "Coldplay",
            "note": ""
        },
        {
            "type": "spotify",
            "id": "2g2GkH3vZHk4lWzBjgQ6nY",
            "day_of_year": "05/18",
            "song": "(What A) Wonderful World",
            "artist": "Sam Cooke",
            "note": ""
        },
        {
            "type": "spotify",
            "id": "4MKZSY7Tkayq3w6KfuB7rQ",
            "day_of_year": "05/19",
            "song": "Contigo Quiero Estar",
            "artist": "Selena",
            "note": ""
        },
        {
            "type": "spotify",
            "id": "3EtIraJEHVSbBvLw5msioH",
            "day_of_year": "05/20",
            "song": "Northern Sky",
            "artist": "Nick Drake",
            "note": ""
        },
        {
            "type": "spotify",
            "id": "65vdMBskhx3akkG9vQlSH1",
            "day_of_year": "05/21",
            "song": "And I Love Her",
            "artist": "The Beatles",
            "note": ""
        },
        {
            "type": "spotify",
            "id": "3QmesrvdbPjwf7i40nht1D",
            "day_of_year": "05/22",
            "song": "Everlong (Acoustic Version)",
            "artist": "Foo Fighters",
            "note": ""
        },
        {
            "type": "spotify",
            "id": "4PCRawItOrjbAqZnZTBsca",
            "day_of_year": "05/23",
            "song": "Sleepwalking (Couples Only Dance Prom Night)",
            "artist": "Modest Mouse",
            "note": ""
        },
        {
            "type": "spotify",
            "id": "2UCoEjy14mWDL6o9jW3IYJ",
            "day_of_year": "05/24",
            "song": "Unforgettable",
            "artist": "Nat King Cole",
            "note": ""
        },
        {
            "type": "spotify",
            "id": "2mN9PvVZX0thvOclMwQAju",
            "day_of_year": "05/25",
            "song": "Your Song",
            "artist": "Ellie Goulding",
            "note": ""
        },
        {
            "type": "spotify",
            "id": "5GorFaKkP2mLREQvhSblIg",
            "day_of_year": "05/26",
            "song": "All My Life",
            "artist": "K-Ci & JoJo",
            "note": ""
        },
        {
            "type": "spotify",
            "id": "6vLwOFz5BYeEJPyvgUea2D",
            "day_of_year": "05/27",
            "song": "Factory Of Faith",
            "artist": "Red Hot Chili Peppers",
            "note": "Be my wife!"
        },
        {
            "type": "spotify",
            "id": "3hnxrhVK6hHJYGq6a1XPL7",
            "day_of_year": "05/28",
            "song": "One in A Million",
            "artist": "The Platters",
            "note": ""
        },
        {
            "type": "spotify",
            "id": "3unsLiH5FXmaDWtT5Imolu",
            "day_of_year": "05/29",
            "song": "Fallin'",
            "artist": "Alicia Keys",
            "note": ""
        },
        {
            "type": "spotify",
            "id": "27YD36FUikKxbp3bKSiKGZ",
            "day_of_year": "05/30",
            "song": "First Time",
            "artist": "Seven Lions, SLANDER, Dabin, Dylan Matthew",
            "note": ""
        },
        {
            "type": "spotify",
            "id": "7KA4W4McWYRpgf0fWsJZWB",
            "day_of_year": "05/31",
            "song": "See You Again",
            "artist": "Tyler, the Creator",
            "note": ""
        },
        {
            "type": "spotify",
            "id": "0sKlV58cODrjxGFOyf9IXY",
            "day_of_year": "06/01",
            "song": "The Way You Make Me Feel",
            "artist": "Michael Jackson",
            "note": ""
        },
        {
            "type": "spotify",
            "id": "1J3w85cS3FEmoSKRu2dQJ8",
            "day_of_year": "06/02",
            "song": "Sea of Love",
            "artist": "Cat Power",
            "note": ""
        },
        {
            "type": "spotify",
            "id": "70XHAdaMaoLIOVb1hSaeJ4",
            "day_of_year": "06/03",
            "song": "Any Time At All",
            "artist": "The Beatles",
            "note": ""
        },
        {
            "type": "spotify",
            "id": "4nDkF3fTl7tvkqaEbm3Ibi",
            "day_of_year": "06/04",
            "song": "Tu Eres",
            "artist": "Selena",
            "note": ""
        },
        {
            "type": "spotify",
            "id": "3cnRYoW4nYzIuVPCp7k5iG",
            "day_of_year": "06/05",
            "song": "Breakdown",
            "artist": "Jack Johnson",
            "note": "This song is a reminder to stop and smell the flowers together from time to time."
        },
        {
            "type": "spotify",
            "id": "22lVNnkNGhMuC8MRPAF0YF",
            "day_of_year": "06/06",
            "song": "Sugar Dumpling",
            "artist": "Sam Cooke",
            "note": ""
        },
        {
            "type": "spotify",
            "id": "6SEG8REPRG1T0kVOWTtgTw",
            "day_of_year": "06/07",
            "song": "Made For You",
            "artist": "Alexander Cardinale",
            "note": ""
        },
        {
            "type": "spotify",
            "id": "52HAHV1j93s5B8GoTNI7DJ",
            "day_of_year": "06/08",
            "song": "Oh, Pretty Woman",
            "artist": "Roy Orbison",
            "note": ""
        },
        {
            "type": "spotify",
            "id": "1gjF57siSU8y09XYs4KpRT",
            "day_of_year": "06/09",
            "song": "When I Fall In Love",
            "artist": "Michael Bublé",
            "note": ""
        },
        {
            "type": "spotify",
            "id": "788U1Sqej9M6c4iikuDGxO",
            "day_of_year": "06/10",
            "song": "I've Just Seen A Face",
            "artist": "The Beatles",
            "note": ""
        },
        {
            "type": "spotify",
            "id": "7jTJDt7RWCslzygXM1C3Ja",
            "day_of_year": "06/11",
            "song": "you mean the whole wide world to me",
            "artist": "Christina Perri",
            "note": ""
        },
        {
            "type": "spotify",
            "id": "03VNgdCL9t8aPyvwZecglI",
            "day_of_year": "06/12",
            "song": "More Than Friends",
            "artist": "Jason Mraz, Meghan Trainor",
            "note": ""
        },
        {
            "type": "spotify",
            "id": "3ACQkIMv6nGYHRpPGyS4BK",
            "day_of_year": "06/13",
            "song": "I Could Fall In Love",
            "artist": "Selena",
            "note": ""
        },
        {
            "type": "spotify",
            "id": "5jhfa76FhqtD3Boij6MAKS",
            "day_of_year": "06/14",
            "song": "Love You Madly",
            "artist": "Cake",
            "note": ""
        },
        {
            "type": "spotify",
            "id": "4fYFXbcEDPfl4Yv2Fbwr9Q",
            "day_of_year": "06/15",
            "song": "If",
            "artist": "Red Hot Chili Peppers",
            "note": "And if I saw the sun fall down<br>I'd pick it up and make a crown<br>One that was a perfect fit for you"
        },
        {
            "type": "spotify",
            "id": "1PpuABE4jUvBQaP7rGOaoi",
            "day_of_year": "06/16",
            "song": "Say Hey (I Love You)",
            "artist": " Michael Franti & Spearhead ft. Cherine Anderson",
            "note": ""
        },
        {
            "type": "spotify",
            "id": "7Aobt67JnaF7qN8jCCKvHq",
            "day_of_year": "06/17",
            "song": "Do You Want To Know A Secret",
            "artist": "The Beatles",
            "note": ""
        },
        {
            "type": "spotify",
            "id": "6rjtB7KSIiJ6v9vrACMlqF",
            "day_of_year": "06/18",
            "song": "400 Lux",
            "artist": "Lorde",
            "note": ""
        },
        {
            "type": "spotify",
            "id": "2sevvnMrqH607r5lwk3kFT",
            "day_of_year": "06/19",
            "song": "Is This Love",
            "artist": "Bob Marley And The Wailers",
            "note": ""
        },
        {
            "type": "spotify",
            "id": "5MjAGtm2ihbBK9G30ZN3Ju",
            "day_of_year": "06/20",
            "song": "Dream A Little Dream Of Me",
            "artist": "Ella Fitzgerald, Louis Armstrong",
            "note": ""
        },
        {
            "type": "spotify",
            "id": "5EL8hqM8YQJHKKnzGdahly",
            "day_of_year": "06/21",
            "song": "Dreaming Of You",
            "artist": "Selena",
            "note": ""
        },
        {
            "type": "spotify",
            "id": "7Msq9qojB7yORuJvz49iUy",
            "day_of_year": "06/22",
            "song": "P.S. I Love You",
            "artist": "The Beatles",
            "note": ""
        },
        {
            "type": "spotify",
            "id": "4aKFHJiQxSnA5kX4pqtXkq",
            "day_of_year": "06/23",
            "song": "Would You Like To Take A Walk?",
            "artist": "She & Him",
            "note": ""
        },
        {
            "type": "spotify",
            "id": "36dRGk4xB4VlCdaB0eagnH",
            "day_of_year": "06/24",
            "song": "La Vie En Rose",
            "artist": "Cristin Milioti",
            "note": ""
        }
    ]
}